nlp/__init__.py
nlp/experiments.py
nlp/test.py
nlpexp-0.1.0.dist-info/METADATA
nlpexp-0.1.0.dist-info/WHEEL
nlpexp-0.1.0.dist-info/top_level.txt
nlpexp-0.1.0.dist-info/RECORD
