Metadata-Version: 2.4
Name: nlpExp
Version: 0.1.0
Summary: NLP experiment runner
Author-email: unknown <you@example.com>
License: MIT
Classifier: Programming Language :: Python :: 3
Classifier: License :: OSI Approved :: MIT License
Classifier: Operating System :: OS Independent
Requires-Python: >=3.8
